Workbook

Sheet Dials
A1: Countercite — model dials
A2: Yellow cells are yours to change. Everything else is a formula. Nothing on the other sheets is typed in by hand.
A4: Dial | B4: Value | C4: Note — where this number came from
A5: Average revenue per customer per month | B5: 299 | C5: Practice tier. Blended will fall between Solo $149 and Firm $599.
A6: Cost to serve one customer per month | B6: 45 | C6: COSTED at ~$18.50/customer (2026-08-31). Kept at 45 deliberately as headroom, because flat pricing absorbs heavy users.
A7: Fixed costs per month | B7: 400 | C7: Domain, hosting, tooling, accounting. Excludes your own time and the one-off legal spend.
A8: New customers in month 1 | B8: 3 | C8: Founder outreach, by hand, from the TDI register.
A9: New customers per month at steady state | B9: 9 | C9: [ASSUMPTION] After SEO and referral compound. Unproven.
A10: Months to reach the steady rate | B10: 9 | C10: How long the channel takes to work.
A11: Monthly churn | B11: 0.045 | C11: [ASSUMPTION] 4.5%/mo = ~22 month average life. Solo professional software churns hard.
A12: Target MRR | B12: 30000 | C12: Midpoint of the $20-50k/month band.
A13: Addressable customers (Texas PAs only) | B13: 1708 | C13: MEASURED, from the TDI licence file.

Sheet Summary
A1: Countercite — the questions that matter
A3: Question | B3: Answer | C3: Why it matters
A4: Customers needed to hit the target MRR | B4: =CEILING(Dials!$B$12/Dials!$B$5,1) | C4: The single number the whole plan aims at.
A5: Months to reach the target | B5: =IFERROR(MATCH(TRUE,INDEX(Monthly!$E$3:$E$38>=Dials!$B$12,0),0),"not within 36") | C5: If this says 'not within 36', the growth or churn dial is unrealistic.
A6: Steady-state ceiling (adds ÷ churn) | B6: =IFERROR(Dials!$B$9/Dials!$B$11,0) | C6: Where customer count stops growing. IF THIS IS BELOW THE BREAK-EVEN COUNT, THE BUSINESS NEVER GETS THERE — churn eats it first. The most important cell in the workbook.
A7: Ceiling as a share of the target | B7: =IFERROR(Dials!$B$9/Dials!$B$11/CEILING(Dials!$B$12/Dials!$B$5,1),0) | C7: Above 100% means the target is reachable at these dials. Below means it is not.
A8: MRR at month 12 | B8: =Monthly!E14
A9: MRR at month 24 | B9: =Monthly!E26
A10: MRR at month 36 | B10: =Monthly!E38
A11: Cumulative cash at month 36 | B11: =Monthly!K38 | C11: Negative means the business has not repaid its fixed costs.
A12: Gross margin | B12: =IFERROR(1-Dials!$B$6/Dials!$B$5,0) | C12: Below about 70% and the flat-price model is under strain.
A13: Average customer lifetime (months) | B13: =IFERROR(1/Dials!$B$11,0) | C13: The reciprocal of monthly churn.
A14: Lifetime value | B14: =IFERROR((Dials!$B$5-Dials!$B$6)/Dials!$B$11,0) | C14: Gross-margin LTV. Compare to what an acquisition is allowed to cost.
A15: Market share needed at the target | B15: =IFERROR(CEILING(Dials!$B$12/Dials!$B$5,1)/Dials!$B$13,0) | C15: Denominator is 1,708 active Texas public adjuster licences (TDI file, 2026-08-28). Texas alone, one of three target professions, before Illinois or Florida.

Sheet Monthly
A1: Countercite — 36 months
A2: Month | B2: New adds | C2: Churned | D2: Customers | E2: MRR | F2: ARR run-rate | G2: COGS | H2: Gross profit | I2: Fixed costs | J2: Net | K2: Cumulative | L2: % of break-even
A3: 1 | B3: =ROUND(MIN(Dials!$B$9,Dials!$B$8+(Dials!$B$9-Dials!$B$8)*MIN(1,(A3-1)/Dials!$B$10)),0) | C3: =ROUND(0*Dials!$B$11,1) | D3: =MAX(0,0+B3-C3) | E3: =D3*Dials!$B$5 | F3: =E3*12 | G3: =D3*Dials!$B$6 | H3: =E3-G3 | I3: =Dials!$B$7 | J3: =H3-I3 | K3: =J3 | L3: =IF(Dials!$B$12=0,0,E3/Dials!$B$12)
A4: 2 | B4: =ROUND(MIN(Dials!$B$9,Dials!$B$8+(Dials!$B$9-Dials!$B$8)*MIN(1,(A4-1)/Dials!$B$10)),0) | C4: =ROUND(D3*Dials!$B$11,1) | D4: =MAX(0,D3+B4-C4) | E4: =D4*Dials!$B$5 | F4: =E4*12 | G4: =D4*Dials!$B$6 | H4: =E4-G4 | I4: =Dials!$B$7 | J4: =H4-I4 | K4: =K3+J4 | L4: =IF(Dials!$B$12=0,0,E4/Dials!$B$12)
A5: 3 | B5: =ROUND(MIN(Dials!$B$9,Dials!$B$8+(Dials!$B$9-Dials!$B$8)*MIN(1,(A5-1)/Dials!$B$10)),0) | C5: =ROUND(D4*Dials!$B$11,1) | D5: =MAX(0,D4+B5-C5) | E5: =D5*Dials!$B$5 | F5: =E5*12 | G5: =D5*Dials!$B$6 | H5: =E5-G5 | I5: =Dials!$B$7 | J5: =H5-I5 | K5: =K4+J5 | L5: =IF(Dials!$B$12=0,0,E5/Dials!$B$12)
A6: 4 | B6: =ROUND(MIN(Dials!$B$9,Dials!$B$8+(Dials!$B$9-Dials!$B$8)*MIN(1,(A6-1)/Dials!$B$10)),0) | C6: =ROUND(D5*Dials!$B$11,1) | D6: =MAX(0,D5+B6-C6) | E6: =D6*Dials!$B$5 | F6: =E6*12 | G6: =D6*Dials!$B$6 | H6: =E6-G6 | I6: =Dials!$B$7 | J6: =H6-I6 | K6: =K5+J6 | L6: =IF(Dials!$B$12=0,0,E6/Dials!$B$12)
A7: 5 | B7: =ROUND(MIN(Dials!$B$9,Dials!$B$8+(Dials!$B$9-Dials!$B$8)*MIN(1,(A7-1)/Dials!$B$10)),0) | C7: =ROUND(D6*Dials!$B$11,1) | D7: =MAX(0,D6+B7-C7) | E7: =D7*Dials!$B$5 | F7: =E7*12 | G7: =D7*Dials!$B$6 | H7: =E7-G7 | I7: =Dials!$B$7 | J7: =H7-I7 | K7: =K6+J7 | L7: =IF(Dials!$B$12=0,0,E7/Dials!$B$12)
A8: 6 | B8: =ROUND(MIN(Dials!$B$9,Dials!$B$8+(Dials!$B$9-Dials!$B$8)*MIN(1,(A8-1)/Dials!$B$10)),0) | C8: =ROUND(D7*Dials!$B$11,1) | D8: =MAX(0,D7+B8-C8) | E8: =D8*Dials!$B$5 | F8: =E8*12 | G8: =D8*Dials!$B$6 | H8: =E8-G8 | I8: =Dials!$B$7 | J8: =H8-I8 | K8: =K7+J8 | L8: =IF(Dials!$B$12=0,0,E8/Dials!$B$12)
A9: 7 | B9: =ROUND(MIN(Dials!$B$9,Dials!$B$8+(Dials!$B$9-Dials!$B$8)*MIN(1,(A9-1)/Dials!$B$10)),0) | C9: =ROUND(D8*Dials!$B$11,1) | D9: =MAX(0,D8+B9-C9) | E9: =D9*Dials!$B$5 | F9: =E9*12 | G9: =D9*Dials!$B$6 | H9: =E9-G9 | I9: =Dials!$B$7 | J9: =H9-I9 | K9: =K8+J9 | L9: =IF(Dials!$B$12=0,0,E9/Dials!$B$12)
A10: 8 | B10: =ROUND(MIN(Dials!$B$9,Dials!$B$8+(Dials!$B$9-Dials!$B$8)*MIN(1,(A10-1)/Dials!$B$10)),0) | C10: =ROUND(D9*Dials!$B$11,1) | D10: =MAX(0,D9+B10-C10) | E10: =D10*Dials!$B$5 | F10: =E10*12 | G10: =D10*Dials!$B$6 | H10: =E10-G10 | I10: =Dials!$B$7 | J10: =H10-I10 | K10: =K9+J10 | L10: =IF(Dials!$B$12=0,0,E10/Dials!$B$12)
A11: 9 | B11: =ROUND(MIN(Dials!$B$9,Dials!$B$8+(Dials!$B$9-Dials!$B$8)*MIN(1,(A11-1)/Dials!$B$10)),0) | C11: =ROUND(D10*Dials!$B$11,1) | D11: =MAX(0,D10+B11-C11) | E11: =D11*Dials!$B$5 | F11: =E11*12 | G11: =D11*Dials!$B$6 | H11: =E11-G11 | I11: =Dials!$B$7 | J11: =H11-I11 | K11: =K10+J11 | L11: =IF(Dials!$B$12=0,0,E11/Dials!$B$12)
A12: 10 | B12: =ROUND(MIN(Dials!$B$9,Dials!$B$8+(Dials!$B$9-Dials!$B$8)*MIN(1,(A12-1)/Dials!$B$10)),0) | C12: =ROUND(D11*Dials!$B$11,1) | D12: =MAX(0,D11+B12-C12) | E12: =D12*Dials!$B$5 | F12: =E12*12 | G12: =D12*Dials!$B$6 | H12: =E12-G12 | I12: =Dials!$B$7 | J12: =H12-I12 | K12: =K11+J12 | L12: =IF(Dials!$B$12=0,0,E12/Dials!$B$12)
A13: 11 | B13: =ROUND(MIN(Dials!$B$9,Dials!$B$8+(Dials!$B$9-Dials!$B$8)*MIN(1,(A13-1)/Dials!$B$10)),0) | C13: =ROUND(D12*Dials!$B$11,1) | D13: =MAX(0,D12+B13-C13) | E13: =D13*Dials!$B$5 | F13: =E13*12 | G13: =D13*Dials!$B$6 | H13: =E13-G13 | I13: =Dials!$B$7 | J13: =H13-I13 | K13: =K12+J13 | L13: =IF(Dials!$B$12=0,0,E13/Dials!$B$12)
A14: 12 | B14: =ROUND(MIN(Dials!$B$9,Dials!$B$8+(Dials!$B$9-Dials!$B$8)*MIN(1,(A14-1)/Dials!$B$10)),0) | C14: =ROUND(D13*Dials!$B$11,1) | D14: =MAX(0,D13+B14-C14) | E14: =D14*Dials!$B$5 | F14: =E14*12 | G14: =D14*Dials!$B$6 | H14: =E14-G14 | I14: =Dials!$B$7 | J14: =H14-I14 | K14: =K13+J14 | L14: =IF(Dials!$B$12=0,0,E14/Dials!$B$12)
A15: 13 | B15: =ROUND(MIN(Dials!$B$9,Dials!$B$8+(Dials!$B$9-Dials!$B$8)*MIN(1,(A15-1)/Dials!$B$10)),0) | C15: =ROUND(D14*Dials!$B$11,1) | D15: =MAX(0,D14+B15-C15) | E15: =D15*Dials!$B$5 | F15: =E15*12 | G15: =D15*Dials!$B$6 | H15: =E15-G15 | I15: =Dials!$B$7 | J15: =H15-I15 | K15: =K14+J15 | L15: =IF(Dials!$B$12=0,0,E15/Dials!$B$12)
... A38: 36 | B38: =ROUND(MIN(Dials!$B$9,Dials!$B$8+(Dials!$B$9-Dials!$B$8)*MIN(1,(A38-1)/Dials!$B$10)),0) | C38: =ROUND(D37*Dials!$B$11,1) | D38: =MAX(0,D37+B38-C38) | E38: =D38*Dials!$B$5 | F38: =E38*12 | G38: =D38*Dials!$B$6 | H38: =E38-G38 | I38: =Dials!$B$7 | J38: =H38-I38 | K38: =K37+J38 | L38: =IF(Dials!$B$12=0,0,E38/Dials!$B$12)

Sheet Sensitivity
A1: Steady-state customer ceiling: adds per month ÷ monthly churn
A2: Churn across the top, monthly adds down the side. Red = below the break-even count, which means the business never reaches its target no matter how long it runs.
A4: adds \ churn | B4: 0.02 | C4: 0.03 | D4: 0.04 | E4: 0.05 | F4: 0.06 | G4: 0.08 | H4: 0.1
A5: 2 | B5: =ROUND($A5/B$4,0) | C5: =ROUND($A5/C$4,0) | D5: =ROUND($A5/D$4,0) | E5: =ROUND($A5/E$4,0) | F5: =ROUND($A5/F$4,0) | G5: =ROUND($A5/G$4,0) | H5: =ROUND($A5/H$4,0)
A6: 3 | B6: =ROUND($A6/B$4,0) | C6: =ROUND($A6/C$4,0) | D6: =ROUND($A6/D$4,0) | E6: =ROUND($A6/E$4,0) | F6: =ROUND($A6/F$4,0) | G6: =ROUND($A6/G$4,0) | H6: =ROUND($A6/H$4,0)
A7: 4 | B7: =ROUND($A7/B$4,0) | C7: =ROUND($A7/C$4,0) | D7: =ROUND($A7/D$4,0) | E7: =ROUND($A7/E$4,0) | F7: =ROUND($A7/F$4,0) | G7: =ROUND($A7/G$4,0) | H7: =ROUND($A7/H$4,0)
A8: 5 | B8: =ROUND($A8/B$4,0) | C8: =ROUND($A8/C$4,0) | D8: =ROUND($A8/D$4,0) | E8: =ROUND($A8/E$4,0) | F8: =ROUND($A8/F$4,0) | G8: =ROUND($A8/G$4,0) | H8: =ROUND($A8/H$4,0)
A9: 6 | B9: =ROUND($A9/B$4,0) | C9: =ROUND($A9/C$4,0) | D9: =ROUND($A9/D$4,0) | E9: =ROUND($A9/E$4,0) | F9: =ROUND($A9/F$4,0) | G9: =ROUND($A9/G$4,0) | H9: =ROUND($A9/H$4,0)
A10: 8 | B10: =ROUND($A10/B$4,0) | C10: =ROUND($A10/C$4,0) | D10: =ROUND($A10/D$4,0) | E10: =ROUND($A10/E$4,0) | F10: =ROUND($A10/F$4,0) | G10: =ROUND($A10/G$4,0) | H10: =ROUND($A10/H$4,0)
A11: 10 | B11: =ROUND($A11/B$4,0) | C11: =ROUND($A11/C$4,0) | D11: =ROUND($A11/D$4,0) | E11: =ROUND($A11/E$4,0) | F11: =ROUND($A11/F$4,0) | G11: =ROUND($A11/G$4,0) | H11: =ROUND($A11/H$4,0)
A12: 12 | B12: =ROUND($A12/B$4,0) | C12: =ROUND($A12/C$4,0) | D12: =ROUND($A12/D$4,0) | E12: =ROUND($A12/E$4,0) | F12: =ROUND($A12/F$4,0) | G12: =ROUND($A12/G$4,0) | H12: =ROUND($A12/H$4,0)
A13: 15 | B13: =ROUND($A13/B$4,0) | C13: =ROUND($A13/C$4,0) | D13: =ROUND($A13/D$4,0) | E13: =ROUND($A13/E$4,0) | F13: =ROUND($A13/F$4,0) | G13: =ROUND($A13/G$4,0) | H13: =ROUND($A13/H$4,0)
A15: Break-even customer count for reference: 101 customers at $299/mo = $30,199/mo

Sheet Notes
A1: What is measured, what is assumed
A3: [MEASURED] 1,708 active Texas public adjuster licences as of 2026-08-28, from the Texas Department of Insurance open data file. 981 resident in Texas, 727 licensed here but living elsewhere, 293 of those in Florida. Houston has 112 resident licensees.
A5: [MEASURED] New licences issued: 160 in 2023, 323 in 2024, 274 in 2025, 187 to August 2026. The 2024-25 cohort is 597 people and is the primary launch target.
A7: [RECOSTED 2026-08-31] Real cost to serve is about $10.60/customer/month at 100 customers on the $299 Practice tier: $1.20 of model inference, $8.97 of card processing, and about $0.47 of everything else. The inference figure is computed in api_cost.py from the pipeline the engine actually runs, not estimated -- retrieval is deterministic, so only candidate passage pairs reach a model and cost scales with pairs rather than page count. It replaces an earlier $9 guess that was 7.5x too high. Note what that leaves: card processing is now 85% of cost to serve, so annual billing and ACH on the Firm tier matter more to margin than any model choice. The dial stays at $45 as deliberate headroom, because flat pricing absorbs heavy users and a firm running thousand-page productions costs several times a light one. If the true figure were $120, gross margin would fall from 94% to 60% and the price would need to rise.
A9: [ASSUMPTION] Steady-state adds of 9/month. No channel has been run yet. This is the second most fragile number here.
A11: [ASSUMPTION] Churn of 4.5%/month. No data. Solo-professional software is generally worse than team software, and a public adjuster with no storm has no cases in March.
A13: [NOT ESTABLISHED] Special education advocates and patient advocates cannot be counted at all -- neither is a licensed profession with a public register. The market dial covers Texas public adjusters ONLY, which makes the market-share figure conservative but also means two of three segments are unmodelled.
A15: [CAUTION] Do not add state registries together. An adjuster licensed in Texas is frequently also licensed in Florida and Illinois. The national de-duplicated total is much smaller than the sum of the states.
A17: [THE CELL TO WATCH] Summary!B6, the steady-state ceiling. Adds divided by churn. If that number is below the break-even customer count, the business never reaches its target however long it runs -- churn eats it first. At 9 adds and 4.5% churn the ceiling is 200, comfortably above 101. At 5 adds and 6% churn it is 83, and the business fails. That is the whole risk in one cell.
