Workbook

Sheet Read Me
A1: Five business models - financial workbook
A3: What this is | B3: One model behind the five buildouts. Every figure on every other tab is a formula driven by the Dials tab.
A4: How to use it | B4: Edit ONLY the blue cells on 'Dials'. Everything else recalculates.
A6: Colour legend
A7: Blue text | B7: A hardcoded input or scenario lever. These are the cells you edit.
A8: Black text | B8: A formula. Do not overwrite.
A9: Green text | B9: A link pulling a value from another sheet.
A10: Yellow fill | B10: A key assumption that materially changes the answer.
A12: Tabs
A13: Dials | B13: Every input: commission, target, price, churn, market size, sales rate.
A14: Summary | B14: The five compared: net per customer, LTV, break-even, share of market.
A15: Barrier ... Fire | B15: A 24-month projection per idea.
A17: Sourcing | B17: Apple's 15% commission under the Small Business Program (up to $1M proceeds) is read off Apple's developer page [vendor].
B18: SMB SaaS monthly churn benchmarks of 3-5% are third-party reported and NOT independently confirmed [review].
B19: Market counts are third-party reported [review]; sources are listed in SOURCES.md.
B20: Churn rates, sales rates and the $6,000 target are ASSUMPTIONS. Nobody has paid for any of these products, so no figure here is measured.
A22: The one caveat | B22: Break-even is unaffected by churn; the replacement treadmill is. At 8% monthly churn you replace twice the customers for the same revenue.

Sheet Dials
A1: Dials - edit the blue cells only
A3: Global
A4: Apple commission | B4: 0.15 | C4: 15% under the App Store Small Business Program, up to $1M proceeds [vendor]. Rises to 30% above that threshold.
A5: Monthly net target | B5: 6000 | C5: What you need the business to pay you, net of Apple. ASSUMPTION.
A6: Projection start customers | B6: 0 | C6: Everything starts at zero paying customers.
A8: Per idea
A9: Idea | B9: Price / month | C9: Monthly churn | D9: US market size | E9: New customers / month | F9: Notes
A10: 7 - Barrier survey | B10: 79 | C10: 0.04 | E10: 4 | F10: Market size UNKNOWN - the CASp register was not reachable and no national count was found. Counting it is task zero.
A11: 8 - Behind the wall | B11: 49 | C11: 0.04 | D11: 127394 | E11: 6 | F11: 127,394 residential remodelers, 2020 Census [review]. Largest denominator.
A12: 1 - Templating | B12: 119 | C12: 0.04 | D12: 5951 | E12: 3 | F12: 5,951 countertop businesses [review]. Price raised from $59 to $119 because 2% market share was needed at $59.
A13: 6 - Floor prep | B13: 39 | C13: 0.04 | D13: 13108 | E13: 7 | F13: 13,108 flooring contractors [review]. Churn likely worse than 4% - lowest usage frequency of the five.
A14: 2 - Fire & life-safety | B14: 89 | C14: 0.025 | D14: 19845 | E14: 3 | F14: 19,845 fire protection & security contractors [review], likely ~half are fire-only. Churn set to 2.5%: the frequency tracker holds customers.
A16: Blue = edit. Yellow = the assumptions that most change the answer.

Sheet Summary
A1: Summary - all five compared
A2: Every cell below is a formula driven by Dials. Nothing here is typed.
A4: Idea | B4: Price / mo | C4: Net / mo after Apple | D4: Monthly churn | E4: Lifetime (months) | F4: LTV | G4: Break-even customers | H4: US market size | I4: Share of market needed | J4: Replacements / month
A5: =Dials!A10 -> 7 - Barrier survey | B5: =Dials!B10 -> 79 | C5: =Dials!B10*(1-Dials!$B$4) -> 67.15 | D5: =Dials!C10 -> 0.04 | E5: =IF(Dials!C10=0,0,1/Dials!C10) -> 25 | F5: =IF(Dials!C10=0,0,C5/Dials!C10) -> 1678.75 | G5: =IF(C5=0,0,ROUNDUP(Dials!$B$5/C5,0)) -> 90 | H5: =Dials!D10 -> 0 | I5: =IF(ISNUMBER(Dials!D10),IF(Dials!D10=0,"n/a",G5/Dials!D10),"unknown") -> unknown | J5: =ROUNDUP(G5*Dials!C10,0) -> 4
A6: =Dials!A11 -> 8 - Behind the wall | B6: =Dials!B11 -> 49 | C6: =Dials!B11*(1-Dials!$B$4) -> 41.65 | D6: =Dials!C11 -> 0.04 | E6: =IF(Dials!C11=0,0,1/Dials!C11) -> 25 | F6: =IF(Dials!C11=0,0,C6/Dials!C11) -> 1041.25 | G6: =IF(C6=0,0,ROUNDUP(Dials!$B$5/C6,0)) -> 145 | H6: =Dials!D11 -> 127394 | I6: =IF(ISNUMBER(Dials!D11),IF(Dials!D11=0,"n/a",G6/Dials!D11),"unknown") -> 0.0011382012 | J6: =ROUNDUP(G6*Dials!C11,0) -> 6
A7: =Dials!A12 -> 1 - Templating | B7: =Dials!B12 -> 119 | C7: =Dials!B12*(1-Dials!$B$4) -> 101.15 | D7: =Dials!C12 -> 0.04 | E7: =IF(Dials!C12=0,0,1/Dials!C12) -> 25 | F7: =IF(Dials!C12=0,0,C7/Dials!C12) -> 2528.75 | G7: =IF(C7=0,0,ROUNDUP(Dials!$B$5/C7,0)) -> 60 | H7: =Dials!D12 -> 5951 | I7: =IF(ISNUMBER(Dials!D12),IF(Dials!D12=0,"n/a",G7/Dials!D12),"unknown") -> 0.010082339 | J7: =ROUNDUP(G7*Dials!C12,0) -> 3
A8: =Dials!A13 -> 6 - Floor prep | B8: =Dials!B13 -> 39 | C8: =Dials!B13*(1-Dials!$B$4) -> 33.15 | D8: =Dials!C13 -> 0.04 | E8: =IF(Dials!C13=0,0,1/Dials!C13) -> 25 | F8: =IF(Dials!C13=0,0,C8/Dials!C13) -> 828.75 | G8: =IF(C8=0,0,ROUNDUP(Dials!$B$5/C8,0)) -> 181 | H8: =Dials!D13 -> 13108 | I8: =IF(ISNUMBER(Dials!D13),IF(Dials!D13=0,"n/a",G8/Dials!D13),"unknown") -> 0.013808361 | J8: =ROUNDUP(G8*Dials!C13,0) -> 8
A9: =Dials!A14 -> 2 - Fire & life-safety | B9: =Dials!B14 -> 89 | C9: =Dials!B14*(1-Dials!$B$4) -> 75.65 | D9: =Dials!C14 -> 0.025 | E9: =IF(Dials!C14=0,0,1/Dials!C14) -> 40 | F9: =IF(Dials!C14=0,0,C9/Dials!C14) -> 3026 | G9: =IF(C9=0,0,ROUNDUP(Dials!$B$5/C9,0)) -> 80 | H9: =Dials!D14 -> 19845 | I9: =IF(ISNUMBER(Dials!D14),IF(Dials!D14=0,"n/a",G9/Dials!D14),"unknown") -> 0.0040312421 | J9: =ROUNDUP(G9*Dials!C14,0) -> 2
A11: Break-even is the customer count that hits the monthly net target. It does NOT move with churn - the replacement rate in the last column does.
A12: 'Share of market needed' is the honest ranking. Idea 1 needs ~18x the penetration idea 8 does.
A13: Barrier survey shows 'unknown' because its denominator has not been established. That is the risk, not a missing cell.

Sheet Barrier
A1: 7 - Barrier survey - 24-month projection
A2: Driven entirely by Dials. Churned customers are rounded to whole people, so the curve steps rather than glides.
A4: Price / mo | B4: =Dials!B10 -> 79
A5: Monthly churn | B5: =Dials!C10 -> 0.04
A6: New / month | B6: =Dials!E10 -> 4
A7: Apple commission | B7: =Dials!$B$4 -> 0.15
A9: Month | B9: Customers start | C9: New | D9: Churned | E9: Customers end | F9: Gross MRR | G9: Net MRR after Apple | H9: Cumulative net
A10: 1 | B10: =Dials!$B$6 -> 0 | C10: =$B$6 -> 4 | D10: =ROUND(B10*$B$5,0) -> 0 | E10: =B10+C10-D10 -> 4 | F10: =E10*$B$4 -> 316 | G10: =F10*(1-$B$7) -> 268.6 | H10: =G10 -> 268.6
A11: 2 | B11: =E10 -> 4 | C11: =$B$6 -> 4 | D11: =ROUND(B11*$B$5,0) -> 0 | E11: =B11+C11-D11 -> 8 | F11: =E11*$B$4 -> 632 | G11: =F11*(1-$B$7) -> 537.2 | H11: =H10+G11 -> 805.8
A12: 3 | B12: =E11 -> 8 | C12: =$B$6 -> 4 | D12: =ROUND(B12*$B$5,0) -> 0 | E12: =B12+C12-D12 -> 12 | F12: =E12*$B$4 -> 948 | G12: =F12*(1-$B$7) -> 805.8 | H12: =H11+G12 -> 1611.6
A13: 4 | B13: =E12 -> 12 | C13: =$B$6 -> 4 | D13: =ROUND(B13*$B$5,0) -> 0 | E13: =B13+C13-D13 -> 16 | F13: =E13*$B$4 -> 1264 | G13: =F13*(1-$B$7) -> 1074.4 | H13: =H12+G13 -> 2686
A14: 5 | B14: =E13 -> 16 | C14: =$B$6 -> 4 | D14: =ROUND(B14*$B$5,0) -> 1 | E14: =B14+C14-D14 -> 19 | F14: =E14*$B$4 -> 1501 | G14: =F14*(1-$B$7) -> 1275.85 | H14: =H13+G14 -> 3961.85
A15: 6 | B15: =E14 -> 19 | C15: =$B$6 -> 4 | D15: =ROUND(B15*$B$5,0) -> 1 | E15: =B15+C15-D15 -> 22 | F15: =E15*$B$4 -> 1738 | G15: =F15*(1-$B$7) -> 1477.3 | H15: =H14+G15 -> 5439.15
A16: 7 | B16: =E15 -> 22 | C16: =$B$6 -> 4 | D16: =ROUND(B16*$B$5,0) -> 1 | E16: =B16+C16-D16 -> 25 | F16: =E16*$B$4 -> 1975 | G16: =F16*(1-$B$7) -> 1678.75 | H16: =H15+G16 -> 7117.9
A17: 8 | B17: =E16 -> 25 | C17: =$B$6 -> 4 | D17: =ROUND(B17*$B$5,0) -> 1 | E17: =B17+C17-D17 -> 28 | F17: =E17*$B$4 -> 2212 | G17: =F17*(1-$B$7) -> 1880.2 | H17: =H16+G17 -> 8998.1
A18: 9 | B18: =E17 -> 28 | C18: =$B$6 -> 4 | D18: =ROUND(B18*$B$5,0) -> 1 | E18: =B18+C18-D18 -> 31 | F18: =E18*$B$4 -> 2449 | G18: =F18*(1-$B$7) -> 2081.65 | H18: =H17+G18 -> 11079.75
A19: 10 | B19: =E18 -> 31 | C19: =$B$6 -> 4 | D19: =ROUND(B19*$B$5,0) -> 1 | E19: =B19+C19-D19 -> 34 | F19: =E19*$B$4 -> 2686 | G19: =F19*(1-$B$7) -> 2283.1 | H19: =H18+G19 -> 13362.85
A20: 11 | B20: =E19 -> 34 | C20: =$B$6 -> 4 | D20: =ROUND(B20*$B$5,0) -> 1 | E20: =B20+C20-D20 -> 37 | F20: =E20*$B$4 -> 2923 | G20: =F20*(1-$B$7) -> 2484.55 | H20: =H19+G20 -> 15847.4
A21: 12 | B21: =E20 -> 37 | C21: =$B$6 -> 4 | D21: =ROUND(B21*$B$5,0) -> 1 | E21: =B21+C21-D21 -> 40 | F21: =E21*$B$4 -> 3160 | G21: =F21*(1-$B$7) -> 2686 | H21: =H20+G21 -> 18533.4
A22: 13 | B22: =E21 -> 40 | C22: =$B$6 -> 4 | D22: =ROUND(B22*$B$5,0) -> 2 | E22: =B22+C22-D22 -> 42 | F22: =E22*$B$4 -> 3318 | G22: =F22*(1-$B$7) -> 2820.3 | H22: =H21+G22 -> 21353.7
... A33: 24 | B33: =E32 -> 62 | C33: =$B$6 -> 4 | D33: =ROUND(B33*$B$5,0) -> 2 | E33: =B33+C33-D33 -> 64 | F33: =E33*$B$4 -> 5056 | G33: =F33*(1-$B$7) -> 4297.6 | H33: =H32+G33 -> 61240.8
A35: Month 24 net MRR | B35: =G33 -> 4297.6
A36: Break-even reached in month | B36: =IFERROR(MATCH(TRUE(),INDEX(G10:G33>=Dials!$B$5,0),0),"not within 24 months") -> not within 24 months
A37: Steady-state customers at this sales rate | B37: =IF($B$5=0,0,$B$6/$B$5) -> 100
A38: Steady state = new per month / churn rate. Beyond it, this sales rate cannot grow the business further.

Sheet Wall
A1: 8 - Behind the wall - 24-month projection
A2: Driven entirely by Dials. Churned customers are rounded to whole people, so the curve steps rather than glides.
A4: Price / mo | B4: =Dials!B11 -> 49
A5: Monthly churn | B5: =Dials!C11 -> 0.04
A6: New / month | B6: =Dials!E11 -> 6
A7: Apple commission | B7: =Dials!$B$4 -> 0.15
A9: Month | B9: Customers start | C9: New | D9: Churned | E9: Customers end | F9: Gross MRR | G9: Net MRR after Apple | H9: Cumulative net
A10: 1 | B10: =Dials!$B$6 -> 0 | C10: =$B$6 -> 6 | D10: =ROUND(B10*$B$5,0) -> 0 | E10: =B10+C10-D10 -> 6 | F10: =E10*$B$4 -> 294 | G10: =F10*(1-$B$7) -> 249.9 | H10: =G10 -> 249.9
A11: 2 | B11: =E10 -> 6 | C11: =$B$6 -> 6 | D11: =ROUND(B11*$B$5,0) -> 0 | E11: =B11+C11-D11 -> 12 | F11: =E11*$B$4 -> 588 | G11: =F11*(1-$B$7) -> 499.8 | H11: =H10+G11 -> 749.7
A12: 3 | B12: =E11 -> 12 | C12: =$B$6 -> 6 | D12: =ROUND(B12*$B$5,0) -> 0 | E12: =B12+C12-D12 -> 18 | F12: =E12*$B$4 -> 882 | G12: =F12*(1-$B$7) -> 749.7 | H12: =H11+G12 -> 1499.4
A13: 4 | B13: =E12 -> 18 | C13: =$B$6 -> 6 | D13: =ROUND(B13*$B$5,0) -> 1 | E13: =B13+C13-D13 -> 23 | F13: =E13*$B$4 -> 1127 | G13: =F13*(1-$B$7) -> 957.95 | H13: =H12+G13 -> 2457.35
A14: 5 | B14: =E13 -> 23 | C14: =$B$6 -> 6 | D14: =ROUND(B14*$B$5,0) -> 1 | E14: =B14+C14-D14 -> 28 | F14: =E14*$B$4 -> 1372 | G14: =F14*(1-$B$7) -> 1166.2 | H14: =H13+G14 -> 3623.55
A15: 6 | B15: =E14 -> 28 | C15: =$B$6 -> 6 | D15: =ROUND(B15*$B$5,0) -> 1 | E15: =B15+C15-D15 -> 33 | F15: =E15*$B$4 -> 1617 | G15: =F15*(1-$B$7) -> 1374.45 | H15: =H14+G15 -> 4998
A16: 7 | B16: =E15 -> 33 | C16: =$B$6 -> 6 | D16: =ROUND(B16*$B$5,0) -> 1 | E16: =B16+C16-D16 -> 38 | F16: =E16*$B$4 -> 1862 | G16: =F16*(1-$B$7) -> 1582.7 | H16: =H15+G16 -> 6580.7
A17: 8 | B17: =E16 -> 38 | C17: =$B$6 -> 6 | D17: =ROUND(B17*$B$5,0) -> 2 | E17: =B17+C17-D17 -> 42 | F17: =E17*$B$4 -> 2058 | G17: =F17*(1-$B$7) -> 1749.3 | H17: =H16+G17 -> 8330
A18: 9 | B18: =E17 -> 42 | C18: =$B$6 -> 6 | D18: =ROUND(B18*$B$5,0) -> 2 | E18: =B18+C18-D18 -> 46 | F18: =E18*$B$4 -> 2254 | G18: =F18*(1-$B$7) -> 1915.9 | H18: =H17+G18 -> 10245.9
A19: 10 | B19: =E18 -> 46 | C19: =$B$6 -> 6 | D19: =ROUND(B19*$B$5,0) -> 2 | E19: =B19+C19-D19 -> 50 | F19: =E19*$B$4 -> 2450 | G19: =F19*(1-$B$7) -> 2082.5 | H19: =H18+G19 -> 12328.4
A20: 11 | B20: =E19 -> 50 | C20: =$B$6 -> 6 | D20: =ROUND(B20*$B$5,0) -> 2 | E20: =B20+C20-D20 -> 54 | F20: =E20*$B$4 -> 2646 | G20: =F20*(1-$B$7) -> 2249.1 | H20: =H19+G20 -> 14577.5
A21: 12 | B21: =E20 -> 54 | C21: =$B$6 -> 6 | D21: =ROUND(B21*$B$5,0) -> 2 | E21: =B21+C21-D21 -> 58 | F21: =E21*$B$4 -> 2842 | G21: =F21*(1-$B$7) -> 2415.7 | H21: =H20+G21 -> 16993.2
A22: 13 | B22: =E21 -> 58 | C22: =$B$6 -> 6 | D22: =ROUND(B22*$B$5,0) -> 2 | E22: =B22+C22-D22 -> 62 | F22: =E22*$B$4 -> 3038 | G22: =F22*(1-$B$7) -> 2582.3 | H22: =H21+G22 -> 19575.5
... A33: 24 | B33: =E32 -> 92 | C33: =$B$6 -> 6 | D33: =ROUND(B33*$B$5,0) -> 4 | E33: =B33+C33-D33 -> 94 | F33: =E33*$B$4 -> 4606 | G33: =F33*(1-$B$7) -> 3915.1 | H33: =H32+G33 -> 56560.7
A35: Month 24 net MRR | B35: =G33 -> 3915.1
A36: Break-even reached in month | B36: =IFERROR(MATCH(TRUE(),INDEX(G10:G33>=Dials!$B$5,0),0),"not within 24 months") -> not within 24 months
A37: Steady-state customers at this sales rate | B37: =IF($B$5=0,0,$B$6/$B$5) -> 150
A38: Steady state = new per month / churn rate. Beyond it, this sales rate cannot grow the business further.

Sheet Templating
A1: 1 - Templating - 24-month projection
A2: Driven entirely by Dials. Churned customers are rounded to whole people, so the curve steps rather than glides.
A4: Price / mo | B4: =Dials!B12 -> 119
A5: Monthly churn | B5: =Dials!C12 -> 0.04
A6: New / month | B6: =Dials!E12 -> 3
A7: Apple commission | B7: =Dials!$B$4 -> 0.15
A9: Month | B9: Customers start | C9: New | D9: Churned | E9: Customers end | F9: Gross MRR | G9: Net MRR after Apple | H9: Cumulative net
A10: 1 | B10: =Dials!$B$6 -> 0 | C10: =$B$6 -> 3 | D10: =ROUND(B10*$B$5,0) -> 0 | E10: =B10+C10-D10 -> 3 | F10: =E10*$B$4 -> 357 | G10: =F10*(1-$B$7) -> 303.45 | H10: =G10 -> 303.45
A11: 2 | B11: =E10 -> 3 | C11: =$B$6 -> 3 | D11: =ROUND(B11*$B$5,0) -> 0 | E11: =B11+C11-D11 -> 6 | F11: =E11*$B$4 -> 714 | G11: =F11*(1-$B$7) -> 606.9 | H11: =H10+G11 -> 910.35
A12: 3 | B12: =E11 -> 6 | C12: =$B$6 -> 3 | D12: =ROUND(B12*$B$5,0) -> 0 | E12: =B12+C12-D12 -> 9 | F12: =E12*$B$4 -> 1071 | G12: =F12*(1-$B$7) -> 910.35 | H12: =H11+G12 -> 1820.7
A13: 4 | B13: =E12 -> 9 | C13: =$B$6 -> 3 | D13: =ROUND(B13*$B$5,0) -> 0 | E13: =B13+C13-D13 -> 12 | F13: =E13*$B$4 -> 1428 | G13: =F13*(1-$B$7) -> 1213.8 | H13: =H12+G13 -> 3034.5
A14: 5 | B14: =E13 -> 12 | C14: =$B$6 -> 3 | D14: =ROUND(B14*$B$5,0) -> 0 | E14: =B14+C14-D14 -> 15 | F14: =E14*$B$4 -> 1785 | G14: =F14*(1-$B$7) -> 1517.25 | H14: =H13+G14 -> 4551.75
A15: 6 | B15: =E14 -> 15 | C15: =$B$6 -> 3 | D15: =ROUND(B15*$B$5,0) -> 1 | E15: =B15+C15-D15 -> 17 | F15: =E15*$B$4 -> 2023 | G15: =F15*(1-$B$7) -> 1719.55 | H15: =H14+G15 -> 6271.3
A16: 7 | B16: =E15 -> 17 | C16: =$B$6 -> 3 | D16: =ROUND(B16*$B$5,0) -> 1 | E16: =B16+C16-D16 -> 19 | F16: =E16*$B$4 -> 2261 | G16: =F16*(1-$B$7) -> 1921.85 | H16: =H15+G16 -> 8193.15
A17: 8 | B17: =E16 -> 19 | C17: =$B$6 -> 3 | D17: =ROUND(B17*$B$5,0) -> 1 | E17: =B17+C17-D17 -> 21 | F17: =E17*$B$4 -> 2499 | G17: =F17*(1-$B$7) -> 2124.15 | H17: =H16+G17 -> 10317.3
A18: 9 | B18: =E17 -> 21 | C18: =$B$6 -> 3 | D18: =ROUND(B18*$B$5,0) -> 1 | E18: =B18+C18-D18 -> 23 | F18: =E18*$B$4 -> 2737 | G18: =F18*(1-$B$7) -> 2326.45 | H18: =H17+G18 -> 12643.75
A19: 10 | B19: =E18 -> 23 | C19: =$B$6 -> 3 | D19: =ROUND(B19*$B$5,0) -> 1 | E19: =B19+C19-D19 -> 25 | F19: =E19*$B$4 -> 2975 | G19: =F19*(1-$B$7) -> 2528.75 | H19: =H18+G19 -> 15172.5
A20: 11 | B20: =E19 -> 25 | C20: =$B$6 -> 3 | D20: =ROUND(B20*$B$5,0) -> 1 | E20: =B20+C20-D20 -> 27 | F20: =E20*$B$4 -> 3213 | G20: =F20*(1-$B$7) -> 2731.05 | H20: =H19+G20 -> 17903.55
A21: 12 | B21: =E20 -> 27 | C21: =$B$6 -> 3 | D21: =ROUND(B21*$B$5,0) -> 1 | E21: =B21+C21-D21 -> 29 | F21: =E21*$B$4 -> 3451 | G21: =F21*(1-$B$7) -> 2933.35 | H21: =H20+G21 -> 20836.9
A22: 13 | B22: =E21 -> 29 | C22: =$B$6 -> 3 | D22: =ROUND(B22*$B$5,0) -> 1 | E22: =B22+C22-D22 -> 31 | F22: =E22*$B$4 -> 3689 | G22: =F22*(1-$B$7) -> 3135.65 | H22: =H21+G22 -> 23972.55
... A33: 24 | B33: =E32 -> 45 | C33: =$B$6 -> 3 | D33: =ROUND(B33*$B$5,0) -> 2 | E33: =B33+C33-D33 -> 46 | F33: =E33*$B$4 -> 5474 | G33: =F33*(1-$B$7) -> 4652.9 | H33: =H32+G33 -> 68984.3
A35: Month 24 net MRR | B35: =G33 -> 4652.9
A36: Break-even reached in month | B36: =IFERROR(MATCH(TRUE(),INDEX(G10:G33>=Dials!$B$5,0),0),"not within 24 months") -> not within 24 months
A37: Steady-state customers at this sales rate | B37: =IF($B$5=0,0,$B$6/$B$5) -> 75
A38: Steady state = new per month / churn rate. Beyond it, this sales rate cannot grow the business further.

Sheet FloorPrep
A1: 6 - Floor prep - 24-month projection
A2: Driven entirely by Dials. Churned customers are rounded to whole people, so the curve steps rather than glides.
A4: Price / mo | B4: =Dials!B13 -> 39
A5: Monthly churn | B5: =Dials!C13 -> 0.04
A6: New / month | B6: =Dials!E13 -> 7
A7: Apple commission | B7: =Dials!$B$4 -> 0.15
A9: Month | B9: Customers start | C9: New | D9: Churned | E9: Customers end | F9: Gross MRR | G9: Net MRR after Apple | H9: Cumulative net
A10: 1 | B10: =Dials!$B$6 -> 0 | C10: =$B$6 -> 7 | D10: =ROUND(B10*$B$5,0) -> 0 | E10: =B10+C10-D10 -> 7 | F10: =E10*$B$4 -> 273 | G10: =F10*(1-$B$7) -> 232.05 | H10: =G10 -> 232.05
A11: 2 | B11: =E10 -> 7 | C11: =$B$6 -> 7 | D11: =ROUND(B11*$B$5,0) -> 0 | E11: =B11+C11-D11 -> 14 | F11: =E11*$B$4 -> 546 | G11: =F11*(1-$B$7) -> 464.1 | H11: =H10+G11 -> 696.15
A12: 3 | B12: =E11 -> 14 | C12: =$B$6 -> 7 | D12: =ROUND(B12*$B$5,0) -> 1 | E12: =B12+C12-D12 -> 20 | F12: =E12*$B$4 -> 780 | G12: =F12*(1-$B$7) -> 663 | H12: =H11+G12 -> 1359.15
A13: 4 | B13: =E12 -> 20 | C13: =$B$6 -> 7 | D13: =ROUND(B13*$B$5,0) -> 1 | E13: =B13+C13-D13 -> 26 | F13: =E13*$B$4 -> 1014 | G13: =F13*(1-$B$7) -> 861.9 | H13: =H12+G13 -> 2221.05
A14: 5 | B14: =E13 -> 26 | C14: =$B$6 -> 7 | D14: =ROUND(B14*$B$5,0) -> 1 | E14: =B14+C14-D14 -> 32 | F14: =E14*$B$4 -> 1248 | G14: =F14*(1-$B$7) -> 1060.8 | H14: =H13+G14 -> 3281.85
A15: 6 | B15: =E14 -> 32 | C15: =$B$6 -> 7 | D15: =ROUND(B15*$B$5,0) -> 1 | E15: =B15+C15-D15 -> 38 | F15: =E15*$B$4 -> 1482 | G15: =F15*(1-$B$7) -> 1259.7 | H15: =H14+G15 -> 4541.55
A16: 7 | B16: =E15 -> 38 | C16: =$B$6 -> 7 | D16: =ROUND(B16*$B$5,0) -> 2 | E16: =B16+C16-D16 -> 43 | F16: =E16*$B$4 -> 1677 | G16: =F16*(1-$B$7) -> 1425.45 | H16: =H15+G16 -> 5967
A17: 8 | B17: =E16 -> 43 | C17: =$B$6 -> 7 | D17: =ROUND(B17*$B$5,0) -> 2 | E17: =B17+C17-D17 -> 48 | F17: =E17*$B$4 -> 1872 | G17: =F17*(1-$B$7) -> 1591.2 | H17: =H16+G17 -> 7558.2
A18: 9 | B18: =E17 -> 48 | C18: =$B$6 -> 7 | D18: =ROUND(B18*$B$5,0) -> 2 | E18: =B18+C18-D18 -> 53 | F18: =E18*$B$4 -> 2067 | G18: =F18*(1-$B$7) -> 1756.95 | H18: =H17+G18 -> 9315.15
A19: 10 | B19: =E18 -> 53 | C19: =$B$6 -> 7 | D19: =ROUND(B19*$B$5,0) -> 2 | E19: =B19+C19-D19 -> 58 | F19: =E19*$B$4 -> 2262 | G19: =F19*(1-$B$7) -> 1922.7 | H19: =H18+G19 -> 11237.85
A20: 11 | B20: =E19 -> 58 | C20: =$B$6 -> 7 | D20: =ROUND(B20*$B$5,0) -> 2 | E20: =B20+C20-D20 -> 63 | F20: =E20*$B$4 -> 2457 | G20: =F20*(1-$B$7) -> 2088.45 | H20: =H19+G20 -> 13326.3
A21: 12 | B21: =E20 -> 63 | C21: =$B$6 -> 7 | D21: =ROUND(B21*$B$5,0) -> 3 | E21: =B21+C21-D21 -> 67 | F21: =E21*$B$4 -> 2613 | G21: =F21*(1-$B$7) -> 2221.05 | H21: =H20+G21 -> 15547.35
A22: 13 | B22: =E21 -> 67 | C22: =$B$6 -> 7 | D22: =ROUND(B22*$B$5,0) -> 3 | E22: =B22+C22-D22 -> 71 | F22: =E22*$B$4 -> 2769 | G22: =F22*(1-$B$7) -> 2353.65 | H22: =H21+G22 -> 17901
... A33: 24 | B33: =E32 -> 106 | C33: =$B$6 -> 7 | D33: =ROUND(B33*$B$5,0) -> 4 | E33: =B33+C33-D33 -> 109 | F33: =E33*$B$4 -> 4251 | G33: =F33*(1-$B$7) -> 3613.35 | H33: =H32+G33 -> 51846.6
A35: Month 24 net MRR | B35: =G33 -> 3613.35
A36: Break-even reached in month | B36: =IFERROR(MATCH(TRUE(),INDEX(G10:G33>=Dials!$B$5,0),0),"not within 24 months") -> not within 24 months
A37: Steady-state customers at this sales rate | B37: =IF($B$5=0,0,$B$6/$B$5) -> 175
A38: Steady state = new per month / churn rate. Beyond it, this sales rate cannot grow the business further.

Sheet Fire
A1: 2 - Fire & life-safety - 24-month projection
A2: Driven entirely by Dials. Churned customers are rounded to whole people, so the curve steps rather than glides.
A4: Price / mo | B4: =Dials!B14 -> 89
A5: Monthly churn | B5: =Dials!C14 -> 0.025
A6: New / month | B6: =Dials!E14 -> 3
A7: Apple commission | B7: =Dials!$B$4 -> 0.15
A9: Month | B9: Customers start | C9: New | D9: Churned | E9: Customers end | F9: Gross MRR | G9: Net MRR after Apple | H9: Cumulative net
A10: 1 | B10: =Dials!$B$6 -> 0 | C10: =$B$6 -> 3 | D10: =ROUND(B10*$B$5,0) -> 0 | E10: =B10+C10-D10 -> 3 | F10: =E10*$B$4 -> 267 | G10: =F10*(1-$B$7) -> 226.95 | H10: =G10 -> 226.95
A11: 2 | B11: =E10 -> 3 | C11: =$B$6 -> 3 | D11: =ROUND(B11*$B$5,0) -> 0 | E11: =B11+C11-D11 -> 6 | F11: =E11*$B$4 -> 534 | G11: =F11*(1-$B$7) -> 453.9 | H11: =H10+G11 -> 680.85
A12: 3 | B12: =E11 -> 6 | C12: =$B$6 -> 3 | D12: =ROUND(B12*$B$5,0) -> 0 | E12: =B12+C12-D12 -> 9 | F12: =E12*$B$4 -> 801 | G12: =F12*(1-$B$7) -> 680.85 | H12: =H11+G12 -> 1361.7
A13: 4 | B13: =E12 -> 9 | C13: =$B$6 -> 3 | D13: =ROUND(B13*$B$5,0) -> 0 | E13: =B13+C13-D13 -> 12 | F13: =E13*$B$4 -> 1068 | G13: =F13*(1-$B$7) -> 907.8 | H13: =H12+G13 -> 2269.5
A14: 5 | B14: =E13 -> 12 | C14: =$B$6 -> 3 | D14: =ROUND(B14*$B$5,0) -> 0 | E14: =B14+C14-D14 -> 15 | F14: =E14*$B$4 -> 1335 | G14: =F14*(1-$B$7) -> 1134.75 | H14: =H13+G14 -> 3404.25
A15: 6 | B15: =E14 -> 15 | C15: =$B$6 -> 3 | D15: =ROUND(B15*$B$5,0) -> 0 | E15: =B15+C15-D15 -> 18 | F15: =E15*$B$4 -> 1602 | G15: =F15*(1-$B$7) -> 1361.7 | H15: =H14+G15 -> 4765.95
A16: 7 | B16: =E15 -> 18 | C16: =$B$6 -> 3 | D16: =ROUND(B16*$B$5,0) -> 0 | E16: =B16+C16-D16 -> 21 | F16: =E16*$B$4 -> 1869 | G16: =F16*(1-$B$7) -> 1588.65 | H16: =H15+G16 -> 6354.6
A17: 8 | B17: =E16 -> 21 | C17: =$B$6 -> 3 | D17: =ROUND(B17*$B$5,0) -> 1 | E17: =B17+C17-D17 -> 23 | F17: =E17*$B$4 -> 2047 | G17: =F17*(1-$B$7) -> 1739.95 | H17: =H16+G17 -> 8094.55
A18: 9 | B18: =E17 -> 23 | C18: =$B$6 -> 3 | D18: =ROUND(B18*$B$5,0) -> 1 | E18: =B18+C18-D18 -> 25 | F18: =E18*$B$4 -> 2225 | G18: =F18*(1-$B$7) -> 1891.25 | H18: =H17+G18 -> 9985.8
A19: 10 | B19: =E18 -> 25 | C19: =$B$6 -> 3 | D19: =ROUND(B19*$B$5,0) -> 1 | E19: =B19+C19-D19 -> 27 | F19: =E19*$B$4 -> 2403 | G19: =F19*(1-$B$7) -> 2042.55 | H19: =H18+G19 -> 12028.35
A20: 11 | B20: =E19 -> 27 | C20: =$B$6 -> 3 | D20: =ROUND(B20*$B$5,0) -> 1 | E20: =B20+C20-D20 -> 29 | F20: =E20*$B$4 -> 2581 | G20: =F20*(1-$B$7) -> 2193.85 | H20: =H19+G20 -> 14222.2
A21: 12 | B21: =E20 -> 29 | C21: =$B$6 -> 3 | D21: =ROUND(B21*$B$5,0) -> 1 | E21: =B21+C21-D21 -> 31 | F21: =E21*$B$4 -> 2759 | G21: =F21*(1-$B$7) -> 2345.15 | H21: =H20+G21 -> 16567.35
A22: 13 | B22: =E21 -> 31 | C22: =$B$6 -> 3 | D22: =ROUND(B22*$B$5,0) -> 1 | E22: =B22+C22-D22 -> 33 | F22: =E22*$B$4 -> 2937 | G22: =F22*(1-$B$7) -> 2496.45 | H22: =H21+G22 -> 19063.8
... A33: 24 | B33: =E32 -> 53 | C33: =$B$6 -> 3 | D33: =ROUND(B33*$B$5,0) -> 1 | E33: =B33+C33-D33 -> 55 | F33: =E33*$B$4 -> 4895 | G33: =F33*(1-$B$7) -> 4160.75 | H33: =H32+G33 -> 56510.55
A35: Month 24 net MRR | B35: =G33 -> 4160.75
A36: Break-even reached in month | B36: =IFERROR(MATCH(TRUE(),INDEX(G10:G33>=Dials!$B$5,0),0),"not within 24 months") -> not within 24 months
A37: Steady-state customers at this sales rate | B37: =IF($B$5=0,0,$B$6/$B$5) -> 120
A38: Steady state = new per month / churn rate. Beyond it, this sales rate cannot grow the business further.
